[
        {
                "id": "3e064a27-bec9-43e0-b09f-9b2d8e3ab7d8",
                "stationCd": "A101-01",
                "equipType": "Rack",
                "equipCd": "A1-01",
                "cellCd": "A101-0101",
                "indCd": "F18EF2",
                "indSeq": 0,
                "channelNo": "5",
                "panNo": "03C9",
                "sideCd": "F",
                "cellSeq": 1,
                "printerCd": "",
                "activeFlag": true
        },
        {
                "id": "c6006c1d-362f-48bd-b780-b9345678dc8e",
                "stationCd": "A302-02",
                "equipType": "Rack",
                "equipCd": "A3-02",
                "cellCd": "A302-0202",
                "indCd": "F18DFD",
                "indSeq": 0,
                "channelNo": "5",
                "panNo": "03C9",
                "sideCd": "R",
                "cellSeq": 16,
                "printerCd": "",
                "activeFlag": true
        },
        {
                "id": "ac825c67-ef0f-4ad0-981a-fb6f8ab50689",
                "stationCd": "A302-02",
                "equipType": "Rack",
                "equipCd": "A3-02",
                "cellCd": "A302-0201",
                "indCd": "F8DA17",
                "indSeq": 0,
                "channelNo": "5",
                "panNo": "03C9",
                "sideCd": "F",
                "cellSeq": 15,
                "printerCd": "",
                "activeFlag": true
        },
        {
                "id": "8ba131cd-f34d-4331-898a-f1fa4e29dc88",
                "stationCd": "A302-01",
                "equipType": "Rack",
                "equipCd": "A3-02",
                "cellCd": "A302-0102",
                "indCd": "F18E5B",
                "indSeq": 0,
                "channelNo": "5",
                "panNo": "03C9",
                "sideCd": "R",
                "cellSeq": 14,
                "printerCd": "",
                "activeFlag": true
        },
        {
                "id": "9b4ee514-0b68-4685-bb1a-419a25478d0d",
                "stationCd": "A302-01",
                "equipType": "Rack",
                "equipCd": "A3-02",
                "cellCd": "A302-0101",
                "indCd": "11331E",
                "indSeq": 0,
                "channelNo": "5",
                "panNo": "03C9",
                "sideCd": "F",
                "cellSeq": 13,
                "printerCd": "",
                "activeFlag": true
        },
        {
                "id": "ee2b91d3-db1a-4d03-8415-11a50690c378",
                "stationCd": "A301-02",
                "equipType": "Rack",
                "equipCd": "A3-01",
                "cellCd": "A301-0202",
                "indCd": "F18EF1",
                "indSeq": 0,
                "channelNo": "5",
                "panNo": "03C9",
                "sideCd": "R",
                "cellSeq": 12,
                "printerCd": "",
                "activeFlag": true
        },
        {
                "id": "a01abe28-bae2-4aab-a04a-95ee8bd8c53c",
                "stationCd": "A301-02",
                "equipType": "Rack",
                "equipCd": "A3-01",
                "cellCd": "A301-0201",
                "indCd": "F18F57",
                "indSeq": 0,
                "channelNo": "5",
                "panNo": "03C9",
                "sideCd": "F",
                "cellSeq": 11,
                "printerCd": "",
                "activeFlag": true
        },
        {
                "id": "5f28ce87-27c2-4683-8e7b-1e8eabb09b10",
                "stationCd": "A301-01",
                "equipType": "Rack",
                "equipCd": "A3-01",
                "cellCd": "A301-0102",
                "indCd": "F18ABF",
                "indSeq": 0,
                "channelNo": "5",
                "panNo": "03C9",
                "sideCd": "R",
                "cellSeq": 10,
                "printerCd": "",
                "activeFlag": true
        },
        {
                "id": "6a04bac4-1ed3-47c9-8aee-4164df43d539",
                "stationCd": "A301-01",
                "equipType": "Rack",
                "equipCd": "A3-01",
                "cellCd": "A301-0101",
                "indCd": "F18EFC",
                "indSeq": 0,
                "channelNo": "5",
                "panNo": "03C9",
                "sideCd": "F",
                "cellSeq": 9,
                "printerCd": "",
                "activeFlag": true
        },
        {
                "id": "3e6f2fa8-eb3a-4c0b-b767-debff420b60b",
                "stationCd": "A101-02",
                "equipType": "Rack",
                "equipCd": "A1-01",
                "cellCd": "A101-0202",
                "indCd": "F18E55",
                "indSeq": 0,
                "channelNo": "5",
                "panNo": "03C9",
                "sideCd": "R",
                "cellSeq": 4,
                "printerCd": "",
                "activeFlag": true
        },
        {
                "id": "fb16b54e-a3e7-49e9-a307-80c7fe3dd688",
                "stationCd": "A101-02",
                "equipType": "Rack",
                "equipCd": "A1-01",
                "cellCd": "A101-0201",
                "indCd": "F18E1A",
                "indSeq": 0,
                "channelNo": "5",
                "panNo": "03C9",
                "sideCd": "F",
                "cellSeq": 3,
                "printerCd": "",
                "activeFlag": true
        },
        {
                "id": "8f6085f4-06a0-4e50-9f62-e9cab89c41a2",
                "stationCd": "A101-01",
                "equipType": "Rack",
                "equipCd": "A1-01",
                "cellCd": "A101-0102",
                "indCd": "F18EAB",
                "indSeq": 0,
                "channelNo": "5",
                "panNo": "03C9",
                "sideCd": "R",
                "cellSeq": 2,
                "printerCd": "",
                "activeFlag": true
        },
        {
                "id": "09f9f876-5fbc-41cc-a8f3-db5b99dc39c3",
                "stationCd": "A201-01",
                "equipType": "Rack",
                "equipCd": "A2-01",
                "cellCd": "A201-0101",
                "indCd": "F18F5B",
                "indSeq": 0,
                "channelNo": "5",
                "panNo": "03C9",
                "sideCd": "F",
                "cellSeq": 1,
                "printerCd": "",
                "activeFlag": true
        },
        {
                "id": "9b109cf5-411f-47a2-87d1-eafee6cd6afb",
                "stationCd": "A201-01",
                "equipType": "Rack",
                "equipCd": "A2-01",
                "cellCd": "A201-0102",
                "indCd": "F8BD48",
                "indSeq": 0,
                "channelNo": "5",
                "panNo": "03C9",
                "sideCd": "F",
                "cellSeq": 2,
                "printerCd": "",
                "activeFlag": true
        },
        {
                "id": "e9f32b45-da6c-47a0-9a27-b4c5db3b1078",
                "stationCd": "A201-01",
                "equipType": "Rack",
                "equipCd": "A2-01",
                "cellCd": "A201-0131",
                "indCd": "F8BD77",
                "indSeq": 0,
                "channelNo": "5",
                "panNo": "03C9",
                "sideCd": "F",
                "cellSeq": 31,
                "activeFlag": true
        },
        {
                "id": "0f6b3946-b1ad-42e8-a178-6bb1b6830f39",
                "stationCd": "A201-01",
                "equipType": "Rack",
                "equipCd": "A2-01",
                "cellCd": "A201-0132",
                "indCd": "F8BD78",
                "indSeq": 0,
                "channelNo": "5",
                "panNo": "03C9",
                "sideCd": "F",
                "cellSeq": 32,
                "activeFlag": true
        },
        {
                "id": "b5ed5758-e9b4-43ba-883b-061ca3e2bb54",
                "stationCd": "A201-01",
                "equipType": "Rack",
                "equipCd": "A2-01",
                "cellCd": "A201-0103",
                "indCd": "F8BD49",
                "indSeq": 0,
                "channelNo": "5",
                "panNo": "03C9",
                "sideCd": "F",
                "cellSeq": 3,
                "printerCd": "",
                "activeFlag": true
        },
        {
                "id": "bffbbee3-793a-40b5-ab36-23883c7de05c",
                "stationCd": "A201-01",
                "equipType": "Rack",
                "equipCd": "A2-01",
                "cellCd": "A201-0110",
                "indCd": "F8BD56",
                "indSeq": 0,
                "channelNo": "5",
                "panNo": "03C9",
                "sideCd": "F",
                "cellSeq": 10,
                "printerCd": "",
                "activeFlag": true
        },
        {
                "id": "f0d7d8ff-f58e-418b-aa2b-5146307aca86",
                "stationCd": "A201-01",
                "equipType": "Rack",
                "equipCd": "A2-01",
                "cellCd": "A201-0111",
                "indCd": "F8BD57",
                "indSeq": 0,
                "channelNo": "5",
                "panNo": "03C9",
                "sideCd": "F",
                "cellSeq": 11,
                "printerCd": "",
                "activeFlag": true
        },
        {
                "id": "d4aaa6d2-98ff-4cbd-b8a1-53768f2205e1",
                "stationCd": "A201-01",
                "equipType": "Rack",
                "equipCd": "A2-01",
                "cellCd": "A201-0112",
                "indCd": "F8BD58",
                "indSeq": 0,
                "channelNo": "5",
                "panNo": "03C9",
                "sideCd": "F",
                "cellSeq": 12,
                "printerCd": "",
                "activeFlag": true
        },
        {
                "id": "ace51137-678b-4d87-bb49-188b687c4755",
                "stationCd": "A201-01",
                "equipType": "Rack",
                "equipCd": "A2-01",
                "cellCd": "A201-0113",
                "indCd": "F8BD59",
                "indSeq": 0,
                "channelNo": "5",
                "panNo": "03C9",
                "sideCd": "F",
                "cellSeq": 13,
                "printerCd": "",
                "activeFlag": true
        },
        {
                "id": "ef667db4-d8ba-4924-9172-99cb4d17c8b6",
                "stationCd": "A201-01",
                "equipType": "Rack",
                "equipCd": "A2-01",
                "cellCd": "A201-0114",
                "indCd": "F8BD60",
                "indSeq": 0,
                "channelNo": "5",
                "panNo": "03C9",
                "sideCd": "F",
                "cellSeq": 14,
                "printerCd": "",
                "activeFlag": true
        },
        {
                "id": "82f696a4-f5ba-47b4-b723-2866e592bc25",
                "stationCd": "A201-01",
                "equipType": "Rack",
                "equipCd": "A2-01",
                "cellCd": "A201-0115",
                "indCd": "F8BD61",
                "indSeq": 0,
                "channelNo": "5",
                "panNo": "03C9",
                "sideCd": "F",
                "cellSeq": 15,
                "printerCd": "",
                "activeFlag": true
        },
        {
                "id": "4c332b16-4e65-4466-81c9-041df76b76a4",
                "stationCd": "A201-01",
                "equipType": "Rack",
                "equipCd": "A2-01",
                "cellCd": "A201-0116",
                "indCd": "F8BD62",
                "indSeq": 0,
                "channelNo": "5",
                "panNo": "03C9",
                "sideCd": "F",
                "cellSeq": 16,
                "printerCd": "",
                "activeFlag": true
        },
        {
                "id": "ca46c8f0-eddd-4729-9dd9-3022f9831c23",
                "stationCd": "A201-02",
                "equipType": "Rack",
                "equipCd": "A2-01",
                "cellCd": "A201-0201",
                "indCd": "F18C91",
                "indSeq": 0,
                "channelNo": "5",
                "panNo": "03C9",
                "sideCd": "R",
                "cellSeq": 101,
                "printerCd": "",
                "activeFlag": true
        },
        {
                "id": "c95cd490-0d81-4aad-8bff-29c72cf5e825",
                "stationCd": "A201-02",
                "equipType": "Rack",
                "equipCd": "A2-01",
                "cellCd": "A201-0202",
                "indCd": "F18EF3",
                "indSeq": 0,
                "channelNo": "5",
                "panNo": "03C9",
                "sideCd": "R",
                "cellSeq": 102,
                "printerCd": "",
                "activeFlag": true
        },
        {
                "id": "8bfb0ff9-5ce8-4dd2-889e-ce8964232ccf",
                "stationCd": "A201-01",
                "equipType": "Rack",
                "equipCd": "A2-01",
                "cellCd": "A201-0133",
                "indCd": "F8BD79",
                "indSeq": 0,
                "channelNo": "5",
                "panNo": "03C9",
                "sideCd": "F",
                "cellSeq": 33,
                "activeFlag": true
        },
        {
                "id": "e959c0a2-0cd9-4530-b182-ebac5ba99c82",
                "stationCd": "A201-01",
                "equipType": "Rack",
                "equipCd": "A2-01",
                "cellCd": "A201-0134",
                "indCd": "F8BD80",
                "indSeq": 0,
                "channelNo": "5",
                "panNo": "03C9",
                "sideCd": "F",
                "cellSeq": 34,
                "activeFlag": true
        },
        {
                "id": "53fe7c17-703e-4d57-a1f6-2723609bfe2f",
                "stationCd": "A201-01",
                "equipType": "Rack",
                "equipCd": "A2-01",
                "cellCd": "A201-0135",
                "indCd": "F8BD81",
                "indSeq": 0,
                "channelNo": "5",
                "panNo": "03C9",
                "sideCd": "F",
                "cellSeq": 35,
                "activeFlag": true
        },
        {
                "id": "3b814d85-543a-405a-a980-681c51860d3f",
                "stationCd": "A201-01",
                "equipType": "Rack",
                "equipCd": "A2-01",
                "cellCd": "A201-0136",
                "indCd": "F8BD82",
                "indSeq": 0,
                "channelNo": "5",
                "panNo": "03C9",
                "sideCd": "F",
                "cellSeq": 36,
                "activeFlag": true
        },
        {
                "id": "4bdc28b7-ee70-48ee-94d8-63b1462219b4",
                "stationCd": "A201-01",
                "equipType": "Rack",
                "equipCd": "A2-01",
                "cellCd": "A201-0137",
                "indCd": "F8BD83",
                "indSeq": 0,
                "channelNo": "5",
                "panNo": "03C9",
                "sideCd": "F",
                "cellSeq": 37,
                "activeFlag": true
        },
        {
                "id": "bec71e95-eb91-43b9-bae3-38b7c696e45e",
                "stationCd": "A201-01",
                "equipType": "Rack",
                "equipCd": "A2-01",
                "cellCd": "A201-0138",
                "indCd": "F8BD84",
                "indSeq": 0,
                "channelNo": "5",
                "panNo": "03C9",
                "sideCd": "F",
                "cellSeq": 38,
                "activeFlag": true
        },
        {
                "id": "efee8159-8aa2-4dba-978f-3c974d99d5fb",
                "stationCd": "A201-01",
                "equipType": "Rack",
                "equipCd": "A2-01",
                "cellCd": "A201-0139",
                "indCd": "F8BD85",
                "indSeq": 0,
                "channelNo": "5",
                "panNo": "03C9",
                "sideCd": "F",
                "cellSeq": 39,
                "activeFlag": true
        },
        {
                "id": "4d9a44aa-ff21-4ae3-8ddc-1fcd40a2f34f",
                "stationCd": "A201-01",
                "equipType": "Rack",
                "equipCd": "A2-01",
                "cellCd": "A201-0140",
                "indCd": "F8BD86",
                "indSeq": 0,
                "channelNo": "5",
                "panNo": "03C9",
                "sideCd": "F",
                "cellSeq": 40,
                "activeFlag": true
        },
        {
                "id": "78bc356e-99e5-46ee-ba71-5101874e505a",
                "stationCd": "A201-01",
                "equipType": "Rack",
                "equipCd": "A2-01",
                "cellCd": "A201-0141",
                "indCd": "F8BD87",
                "indSeq": 0,
                "channelNo": "5",
                "panNo": "03C9",
                "sideCd": "F",
                "cellSeq": 41,
                "activeFlag": true
        },
        {
                "id": "8a6ab1c1-dea1-49ea-86ec-80a3ecdec3d5",
                "stationCd": "A201-01",
                "equipType": "Rack",
                "equipCd": "A2-01",
                "cellCd": "A201-0142",
                "indCd": "F8BD88",
                "indSeq": 0,
                "channelNo": "5",
                "panNo": "03C9",
                "sideCd": "F",
                "cellSeq": 42,
                "activeFlag": true
        },
        {
                "id": "a0f46029-67ba-4907-8c8d-c1463e0db19d",
                "stationCd": "A201-01",
                "equipType": "Rack",
                "equipCd": "A2-01",
                "cellCd": "A201-0143",
                "indCd": "F8BD89",
                "indSeq": 0,
                "channelNo": "5",
                "panNo": "03C9",
                "sideCd": "F",
                "cellSeq": 43,
                "activeFlag": true
        },
        {
                "id": "18b7c49b-cf31-4391-8d87-4d14ecbcf313",
                "stationCd": "A201-01",
                "equipType": "Rack",
                "equipCd": "A2-01",
                "cellCd": "A201-0144",
                "indCd": "F8BD90",
                "indSeq": 0,
                "channelNo": "5",
                "panNo": "03C9",
                "sideCd": "F",
                "cellSeq": 44,
                "activeFlag": true
        },
        {
                "id": "3e640e39-af48-4549-9f8c-b1c3df9bf3ef",
                "stationCd": "A201-01",
                "equipType": "Rack",
                "equipCd": "A2-01",
                "cellCd": "A201-0145",
                "indCd": "F8BD91",
                "indSeq": 0,
                "channelNo": "5",
                "panNo": "03C9",
                "sideCd": "F",
                "cellSeq": 45,
                "activeFlag": true
        },
        {
                "id": "c56d8aaf-24e7-419a-85b0-38ca887710fa",
                "stationCd": "A201-01",
                "equipType": "Rack",
                "equipCd": "A2-01",
                "cellCd": "A201-0146",
                "indCd": "F8BD92",
                "indSeq": 0,
                "channelNo": "5",
                "panNo": "03C9",
                "sideCd": "F",
                "cellSeq": 46,
                "activeFlag": true
        },
        {
                "id": "2bd586e9-ddcc-45f7-af2c-55deddae439c",
                "stationCd": "A201-01",
                "equipType": "Rack",
                "equipCd": "A2-01",
                "cellCd": "A201-0147",
                "indCd": "F8BD93",
                "indSeq": 0,
                "channelNo": "5",
                "panNo": "03C9",
                "sideCd": "F",
                "cellSeq": 47,
                "activeFlag": true
        },
        {
                "id": "ce612580-1b22-4a5d-9863-a91378817757",
                "stationCd": "A201-01",
                "equipType": "Rack",
                "equipCd": "A2-01",
                "cellCd": "A201-0148",
                "indCd": "F8BD94",
                "indSeq": 0,
                "channelNo": "5",
                "panNo": "03C9",
                "sideCd": "F",
                "cellSeq": 48,
                "activeFlag": true
        },
        {
                "id": "66115e6a-9992-4224-baac-b0b0af40fd8e",
                "stationCd": "A201-01",
                "equipType": "Rack",
                "equipCd": "A2-01",
                "cellCd": "A201-0149",
                "indCd": "F8BD95",
                "indSeq": 0,
                "channelNo": "5",
                "panNo": "03C9",
                "sideCd": "F",
                "cellSeq": 49,
                "activeFlag": true
        },
        {
                "id": "2169dfea-cc65-43f4-ace9-1261bdd685b0",
                "stationCd": "A201-01",
                "equipType": "Rack",
                "equipCd": "A2-01",
                "cellCd": "A201-0150",
                "indCd": "F8BD96",
                "indSeq": 0,
                "channelNo": "5",
                "panNo": "03C9",
                "sideCd": "F",
                "cellSeq": 50,
                "activeFlag": true
        },
        {
                "id": "3fd7f971-fb1a-482b-8519-67450e47f534",
                "stationCd": "A201-01",
                "equipType": "Rack",
                "equipCd": "A2-01",
                "cellCd": "A201-0104",
                "indCd": "F8BD50",
                "indSeq": 0,
                "channelNo": "5",
                "panNo": "03C9",
                "sideCd": "F",
                "cellSeq": 4,
                "printerCd": "",
                "activeFlag": true
        },
        {
                "id": "210b068f-7155-4fad-a7ee-d3bfda11b3db",
                "stationCd": "A201-01",
                "equipType": "Rack",
                "equipCd": "A2-01",
                "cellCd": "A201-0105",
                "indCd": "F8BD51",
                "indSeq": 0,
                "channelNo": "5",
                "panNo": "03C9",
                "sideCd": "F",
                "cellSeq": 5,
                "printerCd": "",
                "activeFlag": true
        },
        {
                "id": "a2509e82-4714-445c-94eb-b1078db5b3a6",
                "stationCd": "A201-01",
                "equipType": "Rack",
                "equipCd": "A2-01",
                "cellCd": "A201-0106",
                "indCd": "F8BD52",
                "indSeq": 0,
                "channelNo": "5",
                "panNo": "03C9",
                "sideCd": "F",
                "cellSeq": 6,
                "printerCd": "",
                "activeFlag": true
        },
        {
                "id": "329d1816-c284-44c9-891f-98e989ce6eca",
                "stationCd": "A201-01",
                "equipType": "Rack",
                "equipCd": "A2-01",
                "cellCd": "A201-0107",
                "indCd": "F8BD53",
                "indSeq": 0,
                "channelNo": "5",
                "panNo": "03C9",
                "sideCd": "F",
                "cellSeq": 7,
                "printerCd": "",
                "activeFlag": true
        },
        {
                "id": "54f202b2-f7de-4eaf-ba22-bbbebf91f2e2",
                "stationCd": "A201-01",
                "equipType": "Rack",
                "equipCd": "A2-01",
                "cellCd": "A201-0108",
                "indCd": "F8BD54",
                "indSeq": 0,
                "channelNo": "5",
                "panNo": "03C9",
                "sideCd": "F",
                "cellSeq": 8,
                "printerCd": "",
                "activeFlag": true
        },
        {
                "id": "eaf063a4-cb11-4a01-90be-f8d6e54b1437",
                "stationCd": "A201-01",
                "equipType": "Rack",
                "equipCd": "A2-01",
                "cellCd": "A201-0109",
                "indCd": "F8BD55",
                "indSeq": 0,
                "channelNo": "5",
                "panNo": "03C9",
                "sideCd": "F",
                "cellSeq": 9,
                "printerCd": "",
                "activeFlag": true
        },
        {
                "id": "8553afb2-a03c-4d4f-9ae1-a948400e4116",
                "stationCd": "A201-01",
                "equipType": "Rack",
                "equipCd": "A2-01",
                "cellCd": "A201-0130",
                "indCd": "F8BD76",
                "indSeq": 0,
                "channelNo": "5",
                "panNo": "03C9",
                "sideCd": "F",
                "cellSeq": 30,
                "activeFlag": true
        },
        {
                "id": "4a0dce2a-414c-4184-a7f5-1affefe02d1f",
                "stationCd": "A201-02",
                "equipType": "Rack",
                "equipCd": "A2-01",
                "cellCd": "A201-0203",
                "indCd": "F18EF4",
                "indSeq": 0,
                "channelNo": "5",
                "panNo": "03C9",
                "sideCd": "R",
                "cellSeq": 103,
                "activeFlag": true
        },
        {
                "id": "026fc063-6e09-47bd-bfcd-96929aca4469",
                "stationCd": "A201-02",
                "equipType": "Rack",
                "equipCd": "A2-01",
                "cellCd": "A201-0204",
                "indCd": "F18EF5",
                "indSeq": 0,
                "channelNo": "5",
                "panNo": "03C9",
                "sideCd": "R",
                "cellSeq": 104,
                "activeFlag": true
        },
        {
                "id": "93a2d8f8-9cd0-4cf9-ac21-0a9fda0e34d4",
                "stationCd": "A201-02",
                "equipType": "Rack",
                "equipCd": "A2-01",
                "cellCd": "A201-0205",
                "indCd": "F18EF6",
                "indSeq": 0,
                "channelNo": "5",
                "panNo": "03C9",
                "sideCd": "R",
                "cellSeq": 105,
                "activeFlag": true
        },
        {
                "id": "a36a891c-ee4e-4ace-9fc8-9b32893b7a50",
                "stationCd": "A201-02",
                "equipType": "Rack",
                "equipCd": "A2-01",
                "cellCd": "A201-0206",
                "indCd": "F18EF7",
                "indSeq": 0,
                "channelNo": "5",
                "panNo": "03C9",
                "sideCd": "R",
                "cellSeq": 106,
                "activeFlag": true
        },
        {
                "id": "00d97d17-1302-44e7-b2c3-02d655cd49d3",
                "stationCd": "A201-02",
                "equipType": "Rack",
                "equipCd": "A2-01",
                "cellCd": "A201-0207",
                "indCd": "F18EF8",
                "indSeq": 0,
                "channelNo": "5",
                "panNo": "03C9",
                "sideCd": "R",
                "cellSeq": 107,
                "activeFlag": true
        },
        {
                "id": "92913224-96ef-4bc7-b41a-1400c031fadd",
                "stationCd": "A201-02",
                "equipType": "Rack",
                "equipCd": "A2-01",
                "cellCd": "A201-0208",
                "indCd": "F18EF9",
                "indSeq": 0,
                "channelNo": "5",
                "panNo": "03C9",
                "sideCd": "R",
                "cellSeq": 108,
                "activeFlag": true
        },
        {
                "id": "94a39ddf-0345-4448-b6cb-83c58e3d2949",
                "stationCd": "A201-02",
                "equipType": "Rack",
                "equipCd": "A2-01",
                "cellCd": "A201-0209",
                "indCd": "F18EF10",
                "indSeq": 0,
                "channelNo": "5",
                "panNo": "03C9",
                "sideCd": "R",
                "cellSeq": 109,
                "activeFlag": true
        },
        {
                "id": "e654118f-9d2f-4c9b-9797-7d448e73b121",
                "stationCd": "A201-02",
                "equipType": "Rack",
                "equipCd": "A2-01",
                "cellCd": "A201-0210",
                "indCd": "F18EF11",
                "indSeq": 0,
                "channelNo": "5",
                "panNo": "03C9",
                "sideCd": "R",
                "cellSeq": 110,
                "activeFlag": true
        },
        {
                "id": "3beb7601-967b-478f-a9a0-97461ee78c1e",
                "stationCd": "A201-02",
                "equipType": "Rack",
                "equipCd": "A2-01",
                "cellCd": "A201-0211",
                "indCd": "F18EF12",
                "indSeq": 0,
                "channelNo": "5",
                "panNo": "03C9",
                "sideCd": "R",
                "cellSeq": 111,
                "activeFlag": true
        },
        {
                "id": "5b4c1e97-9aec-4a3f-9ec6-497730e6d3ae",
                "stationCd": "A201-02",
                "equipType": "Rack",
                "equipCd": "A2-01",
                "cellCd": "A201-0212",
                "indCd": "F18EF13",
                "indSeq": 0,
                "channelNo": "5",
                "panNo": "03C9",
                "sideCd": "R",
                "cellSeq": 112,
                "activeFlag": true
        },
        {
                "id": "3d0ce942-5f48-49bc-b542-592a1c35580d",
                "stationCd": "A201-02",
                "equipType": "Rack",
                "equipCd": "A2-01",
                "cellCd": "A201-0232",
                "indCd": "F18EF33",
                "indSeq": 0,
                "channelNo": "5",
                "panNo": "03C9",
                "sideCd": "R",
                "cellSeq": 132,
                "activeFlag": true
        },
        {
                "id": "f42021f0-c105-43a7-a8ee-8f9124522097",
                "stationCd": "A201-02",
                "equipType": "Rack",
                "equipCd": "A2-01",
                "cellCd": "A201-0233",
                "indCd": "F18EF34",
                "indSeq": 0,
                "channelNo": "5",
                "panNo": "03C9",
                "sideCd": "R",
                "cellSeq": 133,
                "activeFlag": true
        },
        {
                "id": "abaf48c7-1ac9-441b-9a6e-d3186a1be08f",
                "stationCd": "A201-02",
                "equipType": "Rack",
                "equipCd": "A2-01",
                "cellCd": "A201-0234",
                "indCd": "F18EF35",
                "indSeq": 0,
                "channelNo": "5",
                "panNo": "03C9",
                "sideCd": "R",
                "cellSeq": 134,
                "activeFlag": true
        },
        {
                "id": "794a6ff3-47b9-4237-b2fb-03a8e264dfbc",
                "stationCd": "A201-02",
                "equipType": "Rack",
                "equipCd": "A2-01",
                "cellCd": "A201-0235",
                "indCd": "F18EF36",
                "indSeq": 0,
                "channelNo": "5",
                "panNo": "03C9",
                "sideCd": "R",
                "cellSeq": 135,
                "activeFlag": true
        },
        {
                "id": "05833afe-c58c-43c8-b531-4280078c30f6",
                "stationCd": "A201-02",
                "equipType": "Rack",
                "equipCd": "A2-01",
                "cellCd": "A201-0236",
                "indCd": "F18EF37",
                "indSeq": 0,
                "channelNo": "5",
                "panNo": "03C9",
                "sideCd": "R",
                "cellSeq": 136,
                "activeFlag": true
        },
        {
                "id": "5bcac25e-a626-4221-bf2d-49de1f8e6eec",
                "stationCd": "A201-02",
                "equipType": "Rack",
                "equipCd": "A2-01",
                "cellCd": "A201-0237",
                "indCd": "F18EF38",
                "indSeq": 0,
                "channelNo": "5",
                "panNo": "03C9",
                "sideCd": "R",
                "cellSeq": 137,
                "activeFlag": true
        },
        {
                "id": "dd52aeae-d73b-48b1-8666-c07657ba8d01",
                "stationCd": "A201-02",
                "equipType": "Rack",
                "equipCd": "A2-01",
                "cellCd": "A201-0238",
                "indCd": "F18EF39",
                "indSeq": 0,
                "channelNo": "5",
                "panNo": "03C9",
                "sideCd": "R",
                "cellSeq": 138,
                "activeFlag": true
        },
        {
                "id": "7d9115c6-5980-46b7-adf6-7abf5c73b1c3",
                "stationCd": "A201-02",
                "equipType": "Rack",
                "equipCd": "A2-01",
                "cellCd": "A201-0239",
                "indCd": "F18EF40",
                "indSeq": 0,
                "channelNo": "5",
                "panNo": "03C9",
                "sideCd": "R",
                "cellSeq": 139,
                "activeFlag": true
        },
        {
                "id": "c0201c39-eedc-48c3-ada6-2f72d2eeb93c",
                "stationCd": "A201-01",
                "equipType": "Rack",
                "equipCd": "A2-01",
                "cellCd": "A201-0117",
                "indCd": "F8BD63",
                "indSeq": 0,
                "channelNo": "5",
                "panNo": "03C9",
                "sideCd": "F",
                "cellSeq": 17,
                "printerCd": "",
                "activeFlag": true
        },
        {
                "id": "59aa1e46-6318-4c61-a8ae-72a5c2d5cb03",
                "stationCd": "A201-01",
                "equipType": "Rack",
                "equipCd": "A2-01",
                "cellCd": "A201-0118",
                "indCd": "F8BD64",
                "indSeq": 0,
                "channelNo": "5",
                "panNo": "03C9",
                "sideCd": "F",
                "cellSeq": 18,
                "printerCd": "",
                "activeFlag": true
        },
        {
                "id": "3cb80c21-51d8-4e7b-b90a-c32d74e7d423",
                "stationCd": "A201-01",
                "equipType": "Rack",
                "equipCd": "A2-01",
                "cellCd": "A201-0119",
                "indCd": "F8BD65",
                "indSeq": 0,
                "channelNo": "5",
                "panNo": "03C9",
                "sideCd": "F",
                "cellSeq": 19,
                "printerCd": "",
                "activeFlag": true
        },
        {
                "id": "407a7b6f-b598-46e9-80fa-da7ed9034ec0",
                "stationCd": "A201-01",
                "equipType": "Rack",
                "equipCd": "A2-01",
                "cellCd": "A201-0120",
                "indCd": "F8BD66",
                "indSeq": 0,
                "channelNo": "5",
                "panNo": "03C9",
                "sideCd": "F",
                "cellSeq": 20,
                "printerCd": "",
                "activeFlag": true
        },
        {
                "id": "45f91499-11b6-4f7f-a1a8-5cc5cdb6fd14",
                "stationCd": "A201-01",
                "equipType": "Rack",
                "equipCd": "A2-01",
                "cellCd": "A201-0121",
                "indCd": "F8BD67",
                "indSeq": 0,
                "channelNo": "5",
                "panNo": "03C9",
                "sideCd": "F",
                "cellSeq": 21,
                "printerCd": "",
                "activeFlag": true
        },
        {
                "id": "e0517a02-49ab-4c01-a2aa-0a4405646ab0",
                "stationCd": "A201-01",
                "equipType": "Rack",
                "equipCd": "A2-01",
                "cellCd": "A201-0122",
                "indCd": "F8BD68",
                "indSeq": 0,
                "channelNo": "5",
                "panNo": "03C9",
                "sideCd": "F",
                "cellSeq": 22,
                "printerCd": "",
                "activeFlag": true
        },
        {
                "id": "5ebca6bf-8bfd-4c92-90ef-0cf4c7c9ed34",
                "stationCd": "A201-01",
                "equipType": "Rack",
                "equipCd": "A2-01",
                "cellCd": "A201-0123",
                "indCd": "F8BD69",
                "indSeq": 0,
                "channelNo": "5",
                "panNo": "03C9",
                "sideCd": "F",
                "cellSeq": 23,
                "printerCd": "",
                "activeFlag": true
        },
        {
                "id": "791bea7b-bf96-406c-b164-041738d5f9dd",
                "stationCd": "A201-01",
                "equipType": "Rack",
                "equipCd": "A2-01",
                "cellCd": "A201-0124",
                "indCd": "F8BD70",
                "indSeq": 0,
                "channelNo": "5",
                "panNo": "03C9",
                "sideCd": "F",
                "cellSeq": 24,
                "printerCd": "",
                "activeFlag": true
        },
        {
                "id": "05f53c5f-2ddc-4daf-8e3b-0c6f5d70b49c",
                "stationCd": "A201-01",
                "equipType": "Rack",
                "equipCd": "A2-01",
                "cellCd": "A201-0125",
                "indCd": "F8BD71",
                "indSeq": 0,
                "channelNo": "5",
                "panNo": "03C9",
                "sideCd": "F",
                "cellSeq": 25,
                "printerCd": "",
                "activeFlag": true
        },
        {
                "id": "e256c2b6-dd71-4cb7-803b-05fd2f9e30bc",
                "stationCd": "A201-01",
                "equipType": "Rack",
                "equipCd": "A2-01",
                "cellCd": "A201-0126",
                "indCd": "F8BD72",
                "indSeq": 0,
                "channelNo": "5",
                "panNo": "03C9",
                "sideCd": "F",
                "cellSeq": 26,
                "printerCd": "",
                "activeFlag": true
        },
        {
                "id": "a3432657-18e9-4291-aa70-c17a7c93fa41",
                "stationCd": "A201-01",
                "equipType": "Rack",
                "equipCd": "A2-01",
                "cellCd": "A201-0127",
                "indCd": "F8BD73",
                "indSeq": 0,
                "channelNo": "5",
                "panNo": "03C9",
                "sideCd": "F",
                "cellSeq": 27,
                "printerCd": "",
                "activeFlag": true
        },
        {
                "id": "f342ecd7-073f-40a6-9186-8e6bd3c03ad2",
                "stationCd": "A201-01",
                "equipType": "Rack",
                "equipCd": "A2-01",
                "cellCd": "A201-0128",
                "indCd": "F8BD74",
                "indSeq": 0,
                "channelNo": "5",
                "panNo": "03C9",
                "sideCd": "F",
                "cellSeq": 28,
                "printerCd": "",
                "activeFlag": true
        },
        {
                "id": "e4ef80ea-0db6-4e63-affa-ef5a364d6d61",
                "stationCd": "A201-01",
                "equipType": "Rack",
                "equipCd": "A2-01",
                "cellCd": "A201-0129",
                "indCd": "F8BD75",
                "indSeq": 0,
                "channelNo": "5",
                "panNo": "03C9",
                "sideCd": "F",
                "cellSeq": 29,
                "printerCd": "",
                "activeFlag": true
        },
        {
                "id": "7242962e-0427-4f7c-9131-902bdc60eb0a",
                "stationCd": "A201-02",
                "equipType": "Rack",
                "equipCd": "A2-01",
                "cellCd": "A201-0213",
                "indCd": "F18EF14",
                "indSeq": 0,
                "channelNo": "5",
                "panNo": "03C9",
                "sideCd": "R",
                "cellSeq": 113,
                "activeFlag": true
        },
        {
                "id": "98467cc3-81a9-4e99-9468-6abb5cf7bb30",
                "stationCd": "A201-02",
                "equipType": "Rack",
                "equipCd": "A2-01",
                "cellCd": "A201-0214",
                "indCd": "F18EF15",
                "indSeq": 0,
                "channelNo": "5",
                "panNo": "03C9",
                "sideCd": "R",
                "cellSeq": 114,
                "activeFlag": true
        },
        {
                "id": "96788288-22ff-4f4e-994f-55ec34b50d6c",
                "stationCd": "A201-02",
                "equipType": "Rack",
                "equipCd": "A2-01",
                "cellCd": "A201-0215",
                "indCd": "F18EF16",
                "indSeq": 0,
                "channelNo": "5",
                "panNo": "03C9",
                "sideCd": "R",
                "cellSeq": 115,
                "activeFlag": true
        },
        {
                "id": "cb88ecd5-09c0-4337-b9c6-e39b889df856",
                "stationCd": "A201-02",
                "equipType": "Rack",
                "equipCd": "A2-01",
                "cellCd": "A201-0216",
                "indCd": "F18EF17",
                "indSeq": 0,
                "channelNo": "5",
                "panNo": "03C9",
                "sideCd": "R",
                "cellSeq": 116,
                "activeFlag": true
        },
        {
                "id": "8d2809b1-591b-44fc-8823-c498bc7b4025",
                "stationCd": "A201-02",
                "equipType": "Rack",
                "equipCd": "A2-01",
                "cellCd": "A201-0217",
                "indCd": "F18EF18",
                "indSeq": 0,
                "channelNo": "5",
                "panNo": "03C9",
                "sideCd": "R",
                "cellSeq": 117,
                "activeFlag": true
        },
        {
                "id": "208c4328-80d2-468e-b81c-0f7bae27bdb9",
                "stationCd": "A201-02",
                "equipType": "Rack",
                "equipCd": "A2-01",
                "cellCd": "A201-0218",
                "indCd": "F18EF19",
                "indSeq": 0,
                "channelNo": "5",
                "panNo": "03C9",
                "sideCd": "R",
                "cellSeq": 118,
                "activeFlag": true
        },
        {
                "id": "733d0f51-0704-43c3-ba2e-de16324eea8d",
                "stationCd": "A201-02",
                "equipType": "Rack",
                "equipCd": "A2-01",
                "cellCd": "A201-0219",
                "indCd": "F18EF20",
                "indSeq": 0,
                "channelNo": "5",
                "panNo": "03C9",
                "sideCd": "R",
                "cellSeq": 119,
                "activeFlag": true
        },
        {
                "id": "3ef8d99a-30be-4b78-b4b1-2b9a773a4d90",
                "stationCd": "A201-02",
                "equipType": "Rack",
                "equipCd": "A2-01",
                "cellCd": "A201-0220",
                "indCd": "F18EF21",
                "indSeq": 0,
                "channelNo": "5",
                "panNo": "03C9",
                "sideCd": "R",
                "cellSeq": 120,
                "activeFlag": true
        },
        {
                "id": "f44aea6a-4cf3-44ae-ab3e-52b7768a6bfe",
                "stationCd": "A201-02",
                "equipType": "Rack",
                "equipCd": "A2-01",
                "cellCd": "A201-0221",
                "indCd": "F18EF22",
                "indSeq": 0,
                "channelNo": "5",
                "panNo": "03C9",
                "sideCd": "R",
                "cellSeq": 121,
                "activeFlag": true
        },
        {
                "id": "c6cf70ec-b0ac-415a-a3a3-d49dc5745d69",
                "stationCd": "A201-02",
                "equipType": "Rack",
                "equipCd": "A2-01",
                "cellCd": "A201-0222",
                "indCd": "F18EF23",
                "indSeq": 0,
                "channelNo": "5",
                "panNo": "03C9",
                "sideCd": "R",
                "cellSeq": 122,
                "activeFlag": true
        },
        {
                "id": "f1cbaec8-3f3b-4199-bcf6-f2b07957c000",
                "stationCd": "A201-02",
                "equipType": "Rack",
                "equipCd": "A2-01",
                "cellCd": "A201-0223",
                "indCd": "F18EF24",
                "indSeq": 0,
                "channelNo": "5",
                "panNo": "03C9",
                "sideCd": "R",
                "cellSeq": 123,
                "activeFlag": true
        },
        {
                "id": "e4761e06-733f-491b-a8d8-0964d2f5542a",
                "stationCd": "A201-02",
                "equipType": "Rack",
                "equipCd": "A2-01",
                "cellCd": "A201-0224",
                "indCd": "F18EF25",
                "indSeq": 0,
                "channelNo": "5",
                "panNo": "03C9",
                "sideCd": "R",
                "cellSeq": 124,
                "activeFlag": true
        },
        {
                "id": "02599be3-c662-4901-8061-832741c72896",
                "stationCd": "A201-02",
                "equipType": "Rack",
                "equipCd": "A2-01",
                "cellCd": "A201-0225",
                "indCd": "F18EF26",
                "indSeq": 0,
                "channelNo": "5",
                "panNo": "03C9",
                "sideCd": "R",
                "cellSeq": 125,
                "activeFlag": true
        },
        {
                "id": "b117e3d0-49c0-4ae2-9f4c-d1b4e621144b",
                "stationCd": "A201-02",
                "equipType": "Rack",
                "equipCd": "A2-01",
                "cellCd": "A201-0226",
                "indCd": "F18EF27",
                "indSeq": 0,
                "channelNo": "5",
                "panNo": "03C9",
                "sideCd": "R",
                "cellSeq": 126,
                "activeFlag": true
        },
        {
                "id": "8159e739-cdd8-493e-bae9-188535b0e93c",
                "stationCd": "A201-02",
                "equipType": "Rack",
                "equipCd": "A2-01",
                "cellCd": "A201-0227",
                "indCd": "F18EF28",
                "indSeq": 0,
                "channelNo": "5",
                "panNo": "03C9",
                "sideCd": "R",
                "cellSeq": 127,
                "activeFlag": true
        },
        {
                "id": "22c0fb4c-7590-4b88-b6cc-bede2c29e130",
                "stationCd": "A201-02",
                "equipType": "Rack",
                "equipCd": "A2-01",
                "cellCd": "A201-0228",
                "indCd": "F18EF29",
                "indSeq": 0,
                "channelNo": "5",
                "panNo": "03C9",
                "sideCd": "R",
                "cellSeq": 128,
                "activeFlag": true
        },
        {
                "id": "7b15dc78-32c5-47d3-a950-c435e69543cc",
                "stationCd": "A201-02",
                "equipType": "Rack",
                "equipCd": "A2-01",
                "cellCd": "A201-0229",
                "indCd": "F18EF30",
                "indSeq": 0,
                "channelNo": "5",
                "panNo": "03C9",
                "sideCd": "R",
                "cellSeq": 129,
                "activeFlag": true
        },
        {
                "id": "61e9b436-4485-469e-800f-1f639556c3e4",
                "stationCd": "A201-02",
                "equipType": "Rack",
                "equipCd": "A2-01",
                "cellCd": "A201-0230",
                "indCd": "F18EF31",
                "indSeq": 0,
                "channelNo": "5",
                "panNo": "03C9",
                "sideCd": "R",
                "cellSeq": 130,
                "activeFlag": true
        },
        {
                "id": "4cf373f2-d23e-4b16-89bf-d89e48c809d2",
                "stationCd": "A201-02",
                "equipType": "Rack",
                "equipCd": "A2-01",
                "cellCd": "A201-0231",
                "indCd": "F18EF32",
                "indSeq": 0,
                "channelNo": "5",
                "panNo": "03C9",
                "sideCd": "R",
                "cellSeq": 131,
                "activeFlag": true
        },
        {
                "id": "d62ab5d5-2ff2-40f4-b49c-30a6894dce1c",
                "stationCd": "A201-02",
                "equipType": "Rack",
                "equipCd": "A2-01",
                "cellCd": "A201-0240",
                "indCd": "F18EF41",
                "indSeq": 0,
                "channelNo": "5",
                "panNo": "03C9",
                "sideCd": "R",
                "cellSeq": 140,
                "activeFlag": true
        },
        {
                "id": "d3b29aa8-b5f4-4816-a421-0cf685a6b5e8",
                "stationCd": "A201-02",
                "equipType": "Rack",
                "equipCd": "A2-01",
                "cellCd": "A201-0241",
                "indCd": "F18EF42",
                "indSeq": 0,
                "channelNo": "5",
                "panNo": "03C9",
                "sideCd": "R",
                "cellSeq": 141,
                "activeFlag": true
        },
        {
                "id": "899b16a5-6381-41a7-92dc-abe5c1699d60",
                "stationCd": "A201-02",
                "equipType": "Rack",
                "equipCd": "A2-01",
                "cellCd": "A201-0242",
                "indCd": "F18EF43",
                "indSeq": 0,
                "channelNo": "5",
                "panNo": "03C9",
                "sideCd": "R",
                "cellSeq": 142,
                "activeFlag": true
        },
        {
                "id": "86c27690-e44e-4244-8ccb-2ee15fda4f75",
                "stationCd": "A201-02",
                "equipType": "Rack",
                "equipCd": "A2-01",
                "cellCd": "A201-0243",
                "indCd": "F18EF44",
                "indSeq": 0,
                "channelNo": "5",
                "panNo": "03C9",
                "sideCd": "R",
                "cellSeq": 143,
                "activeFlag": true
        },
        {
                "id": "0cbb720c-0e23-41a9-b644-a160aaadf5f9",
                "stationCd": "A201-02",
                "equipType": "Rack",
                "equipCd": "A2-01",
                "cellCd": "A201-0244",
                "indCd": "F18EF45",
                "indSeq": 0,
                "channelNo": "5",
                "panNo": "03C9",
                "sideCd": "R",
                "cellSeq": 144,
                "activeFlag": true
        },
        {
                "id": "bcafa3a1-5651-420f-aa9f-3e126ebda96a",
                "stationCd": "A201-02",
                "equipType": "Rack",
                "equipCd": "A2-01",
                "cellCd": "A201-0245",
                "indCd": "F18EF46",
                "indSeq": 0,
                "channelNo": "5",
                "panNo": "03C9",
                "sideCd": "R",
                "cellSeq": 145,
                "activeFlag": true
        },
        {
                "id": "d5e10abb-6173-4ed1-ad82-f3e61018e2c2",
                "stationCd": "A201-02",
                "equipType": "Rack",
                "equipCd": "A2-01",
                "cellCd": "A201-0246",
                "indCd": "F18EF47",
                "indSeq": 0,
                "channelNo": "5",
                "panNo": "03C9",
                "sideCd": "R",
                "cellSeq": 146,
                "activeFlag": true
        },
        {
                "id": "302aaef1-bc84-4def-bf72-34f0a8987c54",
                "stationCd": "A201-02",
                "equipType": "Rack",
                "equipCd": "A2-01",
                "cellCd": "A201-0247",
                "indCd": "F18EF48",
                "indSeq": 0,
                "channelNo": "5",
                "panNo": "03C9",
                "sideCd": "R",
                "cellSeq": 147,
                "activeFlag": true
        },
        {
                "id": "c7367dc6-f753-4620-a5ad-74d515aecb23",
                "stationCd": "A201-02",
                "equipType": "Rack",
                "equipCd": "A2-01",
                "cellCd": "A201-0248",
                "indCd": "F18EF49",
                "indSeq": 0,
                "channelNo": "5",
                "panNo": "03C9",
                "sideCd": "R",
                "cellSeq": 148,
                "activeFlag": true
        },
        {
                "id": "d121c45b-7e98-4c30-8b77-74ca6b85f756",
                "stationCd": "A201-02",
                "equipType": "Rack",
                "equipCd": "A2-01",
                "cellCd": "A201-0249",
                "indCd": "F18EF50",
                "indSeq": 0,
                "channelNo": "5",
                "panNo": "03C9",
                "sideCd": "R",
                "cellSeq": 149,
                "activeFlag": true
        },
        {
                "id": "aa910ad2-a9ca-4027-b997-500d56c32692",
                "stationCd": "A201-02",
                "equipType": "Rack",
                "equipCd": "A2-01",
                "cellCd": "A201-0250",
                "indCd": "F18EF51",
                "indSeq": 0,
                "channelNo": "5",
                "panNo": "03C9",
                "sideCd": "R",
                "cellSeq": 150,
                "activeFlag": true
        }
]